flater/library/metro/net40/MetroFramework.Design.dll
flater/library/metro/net40/MetroFramework.dll
flater/library/metro/net40/MetroFramework.Fonts.dll
flater/library/metro.py
flater/test.metro.1.py
flater/winforms/metro/__init__.py
flater/winforms/metro/metro_animationbase.py
flater/winforms/metro/metro_button.py
flater/winforms/metro/metro_color_style.txt
flater/winforms/metro/metro_control.py
flater/winforms/metro/metro_form.py
flater/winforms/metro/metro_form.txt
flater/winforms/metro/metro_label.py
flater/winforms/metro/metro_messagebox.py
flater/winforms/metro/metro_panel.py
flater/winforms/metro/metro_style_manager.py
flater/winforms/metro/metro_style_manager.txt
flater/winforms/metro/metro_tab_control.py
flater/winforms/metro/metro_tab_page.py
flater/winforms/metro/metro_tooltip.py
flater_metroframework-0.1.2.dist-info/METADATA
flater_metroframework-0.1.2.dist-info/WHEEL
flater_metroframework-0.1.2.dist-info/RECORD
